{
  "alfredsnippet" : {
    "snippet" : "(cont'd)\n\n\"Even so, in its second year, the London Geological Society was joined by two dozen Fellows of the Royal Society. Its growth accelerated so much that within ten years, its membership was in excess of 400; in 1825, the year of its incorporation, it was up to more than 630. Though England was going through a busy period of canal building and mine exploration (so that there was plenty of digging going on), the number of active geologists who were members of the London Geological Society was very close to zero. The amateurs who were members were interested in geology not so much because of its practical applications or even for the theoretical speculations of a new science, but because of the religious and political consequences it might have.\n\nIn the 18th century, the winds of democracy from America and the attacks of thinkers like Locke and Rousseau, among others, questioned the Monarchy as the natural form of government ...\"\n\n(cont'd)",
    "uid" : "E080475B-BF8A-4B54-9206-F460D2C4B449",
    "name" : "Phys.org Post - Origin of Uniformitarianism - Part 2",
    "keyword" : "pp uniform 2"
  }
}