{
  "alfredsnippet" : {
    "snippet" : "Could gambling save science? Encouraging an honest consensus\nRobin Hanson\n\n\"Consider the example of Piers Corbyn, a London astrophysicist who has been unable to get academic meteorologists interested in his unusual theory of long-term weather cycles (New Scientist, 1990). Since June 1988 he has been making bets to gain publicity, betting against the bookmakers William Hill, who uses odds posted by the British Meteorological Service. He has been winning. Over the 26 months from April 1989 to May 1991, Corbyn has made at least 9 bets a month (and averaged over 20 bets a month) and has won 80% of these bets, gaining an average rate of return of over 25% per bet ...\"\n\n(cont'd)",
    "uid" : "32CAFAE8-8E83-4592-A279-93550ED9FCEE",
    "name" : "Phys.org Post - Piers Corbyn Science Futures Market - Part 1",
    "keyword" : "pp piers corbyn science futures 1"
  }
}