{
  "alfredsnippet" : {
    "snippet" : "\"In the testing of hypotheses lies the prime difference between the investigator and the theorist. The one seeks diligently for the facts which may overthrow his tentative theory. The other closes his eyes to these, and searches only for those which will sustain it.\"\n\n- Grove Karl Gilbert, Chief Geologist of the US Geological Survey, 1895",
    "uid" : "C76D2CBC-EDC1-4E12-BCFA-BE100F2FD2D8",
    "name" : "Phys.org Post - Difference Between an Investigator and a Theorist",
    "keyword" : "pp investigator theorist"
  }
}